SmartAlphaConnect.py
smart_alpha_connect-0.0.2.dist-info/METADATA
smart_alpha_connect-0.0.2.dist-info/WHEEL
smart_alpha_connect-0.0.2.dist-info/top_level.txt
smart_alpha_connect-0.0.2.dist-info/RECORD
