Metadata-Version: 2.1
Name: smart-alpha-connect
Version: 0.0.2
Summary: SmartAlpha Connect
Home-page: https://github.com/LunaticFrisbee/smart-alpha-connect
Author: SmartAlpha
Author-email: Smartalpha2018@gmail.com
License: UNKNOWN
Platform: UNKNOWN
Classifier: Programming Language :: Python :: 3
Classifier: Programming Language :: Python :: 3.6
Classifier: Programming Language :: Python :: 3.7
Classifier: Programming Language :: Python :: 3.8
Classifier: Programming Language :: Python :: 3.9
Classifier: Programming Language :: Python :: 3.10
Classifier: Programming Language :: Python :: 3.11
Classifier: Programming Language :: Python :: 3.12
Classifier: Operating System :: OS Independent
Requires-Dist: requests
